{
    "name": "basic_replace_rules",
    "rules": {
        "〜〜": "〜〜",
        "生る": "生きる",
        "執て": "執って",
        "可らず": "可からず",
        "の全き": "のまっとうき",
        "踰ゆ": "越えゆ",
        "働か": "働",
        "乏しき": "乏き",
        "是時": "この時",
        "瑞士": "スイス",
        "獨乙": "ドイツ",
        "語て": "語りて",
        "を全し": "を全うし",
        "於る": "於ける",
        "從て": "従って",
        "有躰に": "有り体に",
        "如何んぞ": "焉んぞ",
        "是即ち": "これ即ち",
        "可らざ": "可からざ",
        "はるけき": "遥けき",
        "一たび": "ひとたび",
        "なるもの": "なる物",
        "預め": "あらかじめ",
        "を置て": "を置いて",
        "而て": "而して",
        "なること": "なる事",
        "焉ぞ": "焉んぞ",
        "焉くんぞ": "焉んぞ",
        "抑も": "そもそも",
        "弗": "ドル",
        "於て": "於いて",
        "味ひ": "味わい",
        "目醒": "目醒め",
        "斯る": "かかる",
        "新に": "新たに",
        "齎す": "もたらす",
        "依て": "依って",
        "屹度": "きっと",
        "盡さ": "尽くさ",
        "盡し": "尽くし",
        "盡せ": "尽くせ",
        "盡そ": "尽くそ",
        "陷る": "陥いる",
        "せう": "しょう",
        "分らい": "分ら無い",
        "雖ども": "いえども",
        "所謂る": "いわゆる",
        "衝て": "衝いて",
        "驚て": "驚いて",
        "然後": "然る後",
        "甞て": "かつて",
        "答て": "答えて",
        "即はち": "すなわち",
        "况んや": "いわんや",
        "况や": "いわんや",
        "孰れ": "いずれ",
        "樂む": "楽しむ",
        "若夫れ": "もしそれ",
        "成て": "成して",
        "定て": "定めて",
        "對ふ所": "向かう所",
        "怪む": "怪しむ",
        "珍らし": "珍し",
        "怪ま": "怪しま",
        "又將た": "またはた",
        "はるけし": "遥けし",
        "離る": "離れる",
        "擯け": "退け",
        "離るゝ": "離れる",
        "如何ぞ": "焉んぞ",
        "如何ん": "いかん",
        "甞み": "試み",
        "用ふる": "用いる",
        "聚合": "集合",
        "闢き": "開き",
        "闢く": "開く",
        "闢け": "開け",
        "本づき": "基づき",
        "游牧": "遊牧",
        "假令": "たと",
        "冨": "富",
        "亞非利加": "アフリカ",
        "添ふる": "添える",
        "亜非利加": "アフリカ",
        "假令ひ": "たとい",
        "燃ゆる": "燃える",
        "にさへ": "にさえ",
        "盖": "蓋",
        "を反へ": "を変え",
        "徃": "往",
        "刺劇": "刺激",
        "例之ば": "例えば",
        "搆": "構",
        "决": "決",
        "進轉": "進展",
        "進転": "進展",
        "躰": "体",
        "具なへ": "そなえ",
        "若かず": "しかず",
        "へる": "える",
        "數": "数",
        "舊": "旧",
        "黨": "党",
        "辯": "弁",
        "聽": "聴",
        "余又": "我又",
        "なかつた": "なかった",
        "勞": "労",
        "眞": "真",
        "やつて": "やって",
        "濫賞": "乱賞",
        "云ふ": "言う",
        "といはゞ": "と言わば",
        "廣く": "広く",
        "團": "団",
        "體": "体",
        "斬んな": "そんな",
        "變": "変",
        "モツト": "もっと",
        "單": "単",
        "占むる": "占める",
        "だらう": "だろう",
        "爲": "為",
        "しつとり": "しっとり",
        "といふか": "というか",
        "いとどし": "いただし",
        "ぼつねん": "ぽつねん",
        "かひく": "かいく",
        "かゝへて": "かかえて",
        "たからう": "たかろう",
        "國": "国",
        "囘": "回",
        "對": "対",
        "豐": "豊",
        "簇": "叢",
        "擇": "選",
        "續": "続",
        "姑く": "暫く",
        "擧": "挙",
        "實": "実",
        "將た又": "果て又",
        "獨": "独",
        "經": "経",
        "濟": "済",
        "會": "会",
        "缺": "欠",
        "陷": "陥",
        "戰": "戦",
        "爲る": "する",
        "營": "営",
        "爭": "争",
        "聲": "声",
        "來": "来",
        "濫設": "乱設",
        "收": "収",
        "となつて": "となって",
        "ズツト": "ずっと",
        "豫": "予",
        "やつと": "やっと",
        "萬": "万",
        "圓": "円",
        "與み": "くみ",
        "拔": "抜",
        "兩": "両",
        "樣": "様",
        "效": "効",
        "引つ張": "引っ張",
        "委讓": "委譲",
        "あまへ": "あまえ",
        "かへり": "かえり",
        "くひしば": "食いしば",
        "せはしき": "せわしき",
        "尚ほ": "なお",
        "はづま": "はずま",
        "けはしく": "けわしく",
        "しやべり": "しゃべり",
        "まはつた": "まわった",
        "すれ〜゛": "すれすれ",
        "はづんで": "はずんで",
        "塲": "場",
        "夫れ": "それ",
        "ゑ": "え",
        "ゐ": "い",
        "猶ほ": "なお",
        "問はん": "問わん",
        "收む": "修む",
        "例めし": "ためし",
        "破壞": "破壊",
        "蹈": "踏",
        "活道": "活動",
        "皷": "鼓",
        "葢": "蓋",
        "宜べなる": "うべなる",
        "慶徴": "慶兆",
        "而かも": "しかも",
        "相伍": "相互",
        "閲み": "けみ",
        "どかんか": "退かぬか",
        "かゞ": "かが",
        "きゞ": "きぎ",
        "くゞ": "くぐ",
        "けゞ": "けげ",
        "こゞ": "こご",
        "さゞ": "さざ",
        "しゞ": "しじ",
        "すゞ": "すず",
        "せゞ": "せぜ",
        "そゞ": "そぞ",
        "たゞ": "ただ",
        "ちゞ": "ちぢ",
        "つゞ": "つづ",
        "てゞ": "てで",
        "とゞ": "とど",
        "はゞ": "はば",
        "ひゞ": "ひび",
        "ふゞ": "ふぶ",
        "へゞ": "へべ",
        "ほゞ": "ほぼ",
        "觀": "観",
        "盛焔": "猛炎",
        "能はず": "能わず",
        "刺撃": "刺激",
        "抔": "杯",
        "といはん": "と言わん",
        "主裁": "主催",
        "如斯き": "こんな",
        "はあれど": "は有れど",
        "透破": "踏破",
        "更らに": "さらに",
        "爭ふ": "争う",
        "といふ": "と言う",
        "という": "と言う",
        "といは": "と言わ",
        "といわ": "と言わ",
        "といい": "と言い",
        "といひ": "と言い",
        "といへば": "と言えば",
        "といへな": "と言えな",
        "といへる": "と言える",
        "といへず": "と言えず",
        "といへざ": "と言えざ",
        "といえば": "と言えば",
        "といえな": "と言えな",
        "といえる": "と言える",
        "といえず": "と言えず",
        "といえざ": "と言えざ",
        "といつた": "といった",
        "といつて": "といって",
        "離るら": "離れら",
        "離るり": "離れり",
        "離るる": "離れる",
        "離るれ": "離れれ",
        "離るろ": "離れろ",
        "亞": "亜",
        "惡": "悪",
        "壓": "圧",
        "圍": "囲",
        "醫": "医",
        "壹": "壱",
        "稻": "稲",
        "飮": "飲",
        "隱": "隠",
        "羽": "羽",
        "榮": "栄",
        "衞": "衛",
        "益": "益",
        "驛": "駅",
        "悅": "悦",
        "艷": "艶",
        "鹽": "塩",
        "奧": "奥",
        "應": "応",
        "橫": "横",
        "歐": "欧",
        "毆": "殴",
        "穩": "穏",
        "假": "仮",
        "價": "価",
        "畫": "画",
        "懷": "懐",
        "繪": "絵",
        "擴": "拡",
        "殼": "殻",
        "覺": "覚",
        "學": "学",
        "嶽": "岳",
        "樂": "楽",
        "勸": "勧",
        "卷": "巻",
        "寬": "寛",
        "歡": "歓",
        "罐": "缶",
        "閒": "間",
        "關": "関",
        "館": "館",
        "巖": "巌",
        "顏": "顔",
        "歸": "帰",
        "氣": "気",
        "龜": "亀",
        "僞": "偽",
        "戲": "戯",
        "犧": "犠",
        "卻": "却",
        "糺": "糾",
        "據": "拠",
        "峽": "峡",
        "挾": "挟",
        "敎": "教",
        "狹": "狭",
        "鄕": "郷",
        "堯": "尭",
        "曉": "暁",
        "區": "区",
        "驅": "駆",
        "勳": "勲",
        "薰": "薫",
        "羣": "群",
        "徑": "径",
        "惠": "恵",
        "攜": "携",
        "溪": "渓",
        "繼": "継",
        "莖": "茎",
        "螢": "蛍",
        "輕": "軽",
        "鷄": "鶏",
        "藝": "芸",
        "儉": "倹",
        "劍": "剣",
        "圈": "圏",
        "檢": "検",
        "權": "権",
        "獻": "献",
        "縣": "県",
        "險": "険",
        "顯": "現",
        "驗": "験",
        "嚴": "厳",
        "廣": "広",
        "恆": "恒",
        "鑛": "鉱",
        "號": "号",
        "黑": "黒",
        "碎": "砕",
        "齋": "斎",
        "劑": "剤",
        "冱": "冴",
        "櫻": "桜",
        "册": "冊",
        "雜": "雑",
        "參": "参",
        "慘": "惨",
        "棧": "桟",
        "蠶": "蚕",
        "贊": "賛",
        "殘": "残",
        "絲": "糸",
        "飼": "飼",
        "齒": "歯",
        "兒": "児",
        "辭": "辞",
        "濕": "湿",
        "舍": "舎",
        "寫": "写",
        "釋": "釈",
        "壽": "寿",
        "從": "従",
        "澁": "渋",
        "獸": "獣",
        "縱": "縦",
        "肅": "粛",
        "處": "処",
        "緖": "緒",
        "諸": "諸",
        "敍": "叙",
        "奬": "奨",
        "將": "将",
        "牀": "床",
        "燒": "焼",
        "祥": "祥",
        "稱": "称",
        "證": "証",
        "乘": "乗",
        "剩": "剰",
        "壤": "壌",
        "孃": "嬢",
        "條": "条",
        "淨": "浄",
        "疊": "畳",
        "穰": "穣",
        "讓": "譲",
        "釀": "醸",
        "囑": "嘱",
        "觸": "触",
        "寢": "寝",
        "愼": "慎",
        "晉": "晋",
        "神": "神",
        "刄": "刃",
        "盡": "尽",
        "圖": "図",
        "粹": "粋",
        "醉": "酔",
        "隨": "随",
        "髓": "髄",
        "樞": "枢",
        "瀨": "瀬",
        "晴": "晴",
        "淸": "清",
        "精": "精",
        "靑": "青",
        "靜": "静",
        "齊": "斉",
        "蹟": "跡",
        "攝": "摂",
        "竊": "窃",
        "專": "専",
        "淺": "浅",
        "潛": "潜",
        "纖": "繊",
        "踐": "践",
        "錢": "銭",
        "禪": "禅",
        "曾": "曽",
        "雙": "双",
        "壯": "壮",
        "搜": "捜",
        "插": "挿",
        "窗": "窓",
        "總": "総",
        "聰": "聡",
        "莊": "荘",
        "裝": "装",
        "騷": "騒",
        "增": "増",
        "臟": "臓",
        "藏": "蔵",
        "屬": "属",
        "墮": "堕",
        "帶": "帯",
        "滯": "滞",
        "臺": "台",
        "瀧": "滝",
        "澤": "沢",
        "擔": "担",
        "膽": "胆",
        "彈": "弾",
        "斷": "断",
        "癡": "痴",
        "遲": "遅",
        "晝": "昼",
        "蟲": "虫",
        "鑄": "鋳",
        "猪": "猪",
        "廳": "庁",
        "敕": "勅",
        "鎭": "鎮",
        "塚": "塚",
        "遞": "逓",
        "鐵": "鉄",
        "轉": "転",
        "點": "点",
        "傳": "伝",
        "都": "都",
        "盜": "盗",
        "燈": "灯",
        "當": "当",
        "鬪": "闘",
        "德": "徳",
        "讀": "読",
        "屆": "届",
        "繩": "縄",
        "貳": "弐",
        "姙": "妊",
        "黏": "粘",
        "惱": "悩",
        "腦": "脳",
        "霸": "覇",
        "廢": "廃",
        "拜": "拝",
        "賣": "売",
        "麥": "麦",
        "發": "発",
        "髮": "髪",
        "飯": "飯",
        "蠻": "蛮",
        "祕": "秘",
        "濱": "浜",
        "甁": "瓶",
        "福": "福",
        "拂": "払",
        "佛": "仏",
        "竝": "並",
        "邊": "辺",
        "邉": "辺",
        "辨": "弁",
        "瓣": "弁",
        "舖": "舗",
        "穗": "穂",
        "寶": "宝",
        "萠": "萌",
        "襃": "褒",
        "沒": "没",
        "飜": "翻",
        "槇": "槙",
        "滿": "満",
        "默": "黙",
        "餠": "餅",
        "彌": "弥",
        "藥": "薬",
        "譯": "訳",
        "藪": "薮",
        "餘": "余",
        "與": "与",
        "譽": "誉",
        "搖": "揺",
        "謠": "謡",
        "遙": "遥",
        "瑤": "瑶",
        "慾": "欲",
        "賴": "頼",
        "亂": "乱",
        "覽": "覧",
        "畧": "略",
        "隆": "隆",
        "龍": "竜",
        "獵": "猟",
        "綠": "緑",
        "鄰": "隣",
        "凛": "凜",
        "壘": "塁",
        "勵": "励",
        "禮": "礼",
        "隸": "隷",
        "靈": "霊",
        "齡": "齢",
        "戀": "恋",
        "爐": "炉",
        "朗": "朗",
        "樓": "楼",
        "郞": "郎",
        "祿": "禄",
        "亙": "亘",
        "灣": "湾"
    },
    "condition": "True",
    "notes": "global rules"
}
